stringebraic/__init__.py
stringebraic/__main__.py
stringebraic/helpers.py
stringebraic-0.2.2.dist-info/licenses/LICENSE
stringebraic-0.2.2.dist-info/METADATA
stringebraic-0.2.2.dist-info/WHEEL
stringebraic-0.2.2.dist-info/entry_points.txt
stringebraic-0.2.2.dist-info/top_level.txt
stringebraic-0.2.2.dist-info/RECORD
