Metadata-Version: 2.4
Name: stringebraic
Version: 0.2.2
Summary: String-based Pauli algebraic manipulations
Author-email: Ka Wa Yip <yipkawa@gmail.com>
License: MIT License
Project-URL: Homepage, https://github.com/kwyip/stringebraic
Project-URL: Issues, https://github.com/kwyip/stringebraic/issues
Keywords: Pauli,quantum,inner product
Classifier: Programming Language :: Python
Classifier: Programming Language :: Python :: 3
Classifier: Programming Language :: Python :: 3.8
Classifier: Programming Language :: Python :: 3.9
Classifier: Programming Language :: Python :: 3.10
Classifier: Programming Language :: Python :: 3.11
Classifier: Programming Language :: Python :: 3.12
Classifier: Programming Language :: Python :: 3.13
Requires-Python: >=3.8
License-File: LICENSE
Requires-Dist: pandas>=1.3.1
Requires-Dist: numpy; python_version >= "3.1.0"
Provides-Extra: build
Requires-Dist: build; extra == "build"
Requires-Dist: twine; extra == "build"
Provides-Extra: dev
Requires-Dist: black; extra == "dev"
Requires-Dist: bumpver; extra == "dev"
Requires-Dist: isort; extra == "dev"
Requires-Dist: mypy; extra == "dev"
Requires-Dist: pytest; extra == "dev"
Dynamic: license-file
